sm.py
smModule-9.1.1.dist-info/LICENSE.txt
smModule-9.1.1.dist-info/METADATA
smModule-9.1.1.dist-info/WHEEL
smModule-9.1.1.dist-info/top_level.txt
smModule-9.1.1.dist-info/RECORD
