Metadata-Version: 2.1
Name: smModule
Version: 9.1.1
Summary: Doc for module is now in the module itself
Home-page: UNKNOWN
Author: Pascal Vallaster
Author-email: pascalvallaster@gmail.com
License: UNKNOWN
Platform: UNKNOWN
Classifier: Programming Language :: Python :: 3
Classifier: License :: OSI Approved :: MIT License
Classifier: Operating System :: OS Independent
Requires-Python: >=3.6
License-File: LICENSE.txt
